comfy_monday_api-0.1.0.dist-info/licenses/LICENSE
src/__init__.py
src/activities.py
src/base.py
src/boards.py
src/files.py
src/items.py
src/subscribers.py
src/tags.py
src/teams.py
src/updates.py
src/users.py
comfy_monday_api-0.1.0.dist-info/METADATA
comfy_monday_api-0.1.0.dist-info/WHEEL
comfy_monday_api-0.1.0.dist-info/top_level.txt
comfy_monday_api-0.1.0.dist-info/RECORD
